article_mcp/__init__.py
article_mcp/__main__.py
article_mcp/cli.py
article_mcp/middleware.py
article_mcp/resources.py
article_mcp/middleware/__init__.py
article_mcp/middleware/logging.py
article_mcp/resources/__init__.py
article_mcp/resources/config_resources.py
article_mcp/resources/journal_resources.py
article_mcp/services/__init__.py
article_mcp/services/api_utils.py
article_mcp/services/arxiv_search.py
article_mcp/services/crossref_service.py
article_mcp/services/error_utils.py
article_mcp/services/europe_pmc.py
article_mcp/services/html_to_markdown.py
article_mcp/services/literature_relation_service.py
article_mcp/services/mcp_config.py
article_mcp/services/merged_results.py
article_mcp/services/openalex_service.py
article_mcp/services/pubmed_search.py
article_mcp/services/reference_service.py
article_mcp/services/similar_articles.py
article_mcp/tools/__init__.py
article_mcp/tools/core/__init__.py
article_mcp/tools/core/article_tools.py
article_mcp/tools/core/batch_tools.py
article_mcp/tools/core/quality_tools.py
article_mcp/tools/core/reference_tools.py
article_mcp/tools/core/relation_tools.py
article_mcp/tools/core/search_tools.py
iflow_mcp_article_mcp-0.1.8.dist-info/METADATA
iflow_mcp_article_mcp-0.1.8.dist-info/WHEEL
iflow_mcp_article_mcp-0.1.8.dist-info/entry_points.txt
iflow_mcp_article_mcp-0.1.8.dist-info/top_level.txt
iflow_mcp_article_mcp-0.1.8.dist-info/RECORD
