Metadata-Version: 2.4
Name: iflow-mcp_article-mcp
Version: 0.1.8
Summary: Article MCP文献搜索服务器 - 基于Europe PMC、arXiv等多个数据源的学术文献搜索工具
Author-email: gqy20 <qingyu_ge@foxmail.com>
License-Expression: MIT
Project-URL: Homepage, https://github.com/gqy20/article-mcp
Project-URL: Repository, https://github.com/gqy20/article-mcp
Project-URL: Issues, https://github.com/gqy20/article-mcp/issues
Keywords: mcp,literature,search,europe-pmc,arxiv,academic
Requires-Python: >=3.10
Requires-Dist: fastmcp>=2.13.0
Requires-Dist: requests>=2.25.0
Requires-Dist: python-dateutil>=2.8.0
Requires-Dist: urllib3>=1.26.0
Requires-Dist: aiohttp>=3.9.0
Requires-Dist: markdownify>=0.12.0
Provides-Extra: dev
Requires-Dist: pytest>=7.0.0; extra == "dev"
Requires-Dist: pytest-asyncio>=0.21.0; extra == "dev"
Requires-Dist: pytest-cov>=4.0.0; extra == "dev"
Requires-Dist: black>=23.0.0; extra == "dev"
Requires-Dist: isort>=5.12.0; extra == "dev"
Requires-Dist: ruff>=0.1.0; extra == "dev"
Requires-Dist: mypy>=1.0.0; extra == "dev"
Requires-Dist: pre-commit>=3.0.0; extra == "dev"
Requires-Dist: psutil>=5.9.0; extra == "dev"
